[
    {
        "id": "1",
        "names": [
            {
                "text": "nom test_fr", "lang": "fr"
            },
            {
                "text":"name test _en", "lang":"en"
            }
        ],
        "days": [
            {
                "text":"jour 1", "lang": "fr"
            },
            {
                "text": "day 1", "lang": "en"
            }
        ],
        "season": "summer",
        "icon": "mdi:white-balance-sunny",
        "color": "#FFD700",
        "descriptions": [
            {
                "text": "description Française Lorem ipsum dolor sit amet, consectetur adipiscing elit, sed do eiusmod tempor incididunt ut labore et dolore magna aliqua. Ut enim ad minim veniam, quis nostrud exercitation ullamco laboris nisi ut aliquip ex ea commodo consequat.", "lang": "fr"
            }, 
            {
                "text": "English description Duis aute irure dolor in reprehenderit in voluptate velit esse cillum dolore eu fugiat nulla pariatur", "lang": "en"
            }
        ],
        "equipment_types": [
            {
                "id":"dishwasher",
                "names":[{"name":"Lave-vaisselle","lang":"fr"},{"name":"Dishwasher","lang":"en"}],
                "icon_name":"mdi:dishwasher",
                "color":"#9A7751",
                "isBattery": false,
                "equipmentTypeDurationParams": {
                    "isDurationEditable": true,
                    "isDurationLengthEditable": true,
                    "originalDuration": "00:15",
                    "step": "00:15",
                    "minDuration": "00:15",
                    "maxDuration": "23:45"
                }
            },
            {
                "id":"washingMachine",
                "names":[{"name":"Machine à laver","lang":"fr"},{"name":"Washing-machine","lang":"en"}],
                "icon_name":"mdi:washing-machine",
                "color":"#00447C",
                "isBattery": false,
                "equipmentTypeDurationParams": {
                    "isDurationEditable": true,
                    "isDurationLengthEditable": true,
                    "originalDuration": "00:15",
                    "step": "00:15",
                    "minDuration": "00:15",
                    "maxDuration": "23:45"
                }
            }
        ],
        "initial_consumption": [
            
        ]
    }
]
